recaptcha_manager/__init__.py
recaptcha_manager/exceptions.py
recaptcha_manager/generators.py
recaptcha_manager/manager.py
recaptcha_manager/services.py
recaptcha_manager-0.0.5.dist-info/LICENSE.txt
recaptcha_manager-0.0.5.dist-info/METADATA
recaptcha_manager-0.0.5.dist-info/WHEEL
recaptcha_manager-0.0.5.dist-info/top_level.txt
recaptcha_manager-0.0.5.dist-info/RECORD
