Metadata-Version: 2.1
Name: recaptcha-manager
Version: 0.0.5
Summary: Reduce waiting time for solving recaptchas to less than a second
Home-page: https://www.github.com/charxhit/recaptcha-manager
Author: Charchit Agarwal
Author-email: charchit.a00@gmail.com
License: UNKNOWN
Platform: UNKNOWN
Classifier: Programming Language :: Python :: 3
Classifier: Programming Language :: Python :: 3.5
Classifier: Intended Audience :: Developers
Classifier: License :: OSI Approved :: MIT License
Classifier: Natural Language :: English
Classifier: Operating System :: Microsoft :: Windows
Requires-Python: >=3.5
License-File: LICENSE.txt
Requires-Dist: requests-futures (>=1.0.0) ; platform_system == "Windows"
Requires-Dist: multiprocess ; platform_system == "Windows"
